starplugs/__init__.py
starplugs/starplugs.py
starplugs-0.0.9.dist-info/LICENSE.txt
starplugs-0.0.9.dist-info/METADATA
starplugs-0.0.9.dist-info/WHEEL
starplugs-0.0.9.dist-info/top_level.txt
starplugs-0.0.9.dist-info/RECORD
